{
  "success": true,
  "message": "系统处理成功。",
  "data": {
    "user": [
      {
        "id": 0,
        "tenant_id": 0,
        "tenant_name": "系统租户",
        "account": "SuperAdmin",
        "name": "超级管理员",
        "remark": "该账号是开发人员维护系统用，不能提供给客户使用。",
        "status": 1,
        "superAdmin": true,
        "admin": false
      }
    ],
    "menuList": [
      {
        "id": "AdminHome",
        "name": "首页",
        "route_path": "/admin/home",
        "icon": "iconfont icon-shouye",
        "closable": false,
        "type": 2
      },
      {
        "id": "GRZX",
        "parent_id": "ROOT",
        "parent_name": "系统菜单",
        "parent_path": "/ROOT/",
        "order": 10,
        "children": [
          {
            "id": "GRZX-WDXX",
            "parent_id": "GRZX",
            "parent_name": "个人中心",
            "parent_path": "/ROOT/GRZX/",
            "order": 10,
            "children": [],
            "name": "我的信息",
            "desc": "我的信息页面",
            "icon": "iconfont icon-wodexinxi",
            "type": 2,
            "route_path": "/admin/profile/information",
            "is_web": 101,
            "is_android": 101,
            "is_ios": 102,
            "status": 101,
            "remark": null,
            "urlList": null,
            "full_path": "/ROOT/GRZX/GRZX-WDXX/"
          },
          {
            "id": "GRZX-JCRW",
            "parent_id": "GRZX",
            "parent_name": "个人中心",
            "parent_path": "/ROOT/GRZX/",
            "order": 20,
            "children": [],
            "name": "我的试验任务",
            "desc": "我的试验任务页面",
            "icon": null,
            "type": 2,
            "route_path": "/admin/hnjky/testing/lab/task",
            "is_web": 101,
            "is_android": 102,
            "is_ios": 102,
            "status": 101,
            "remark": null,
            "urlList": null,
            "full_path": "/ROOT/GRZX/GRZX-JCRW/"
          }
        ],
        "name": "个人中心",
        "desc": "个人中心模块",
        "icon": "iconfont icon-gerenzhongxin",
        "type": 1,
        "route_path": null,
        "is_web": 101,
        "is_android": 101,
        "is_ios": 101,
        "status": 101,
        "remark": "日常工作常用功能的快捷入口。",
        "urlList": null,
        "full_path": "/ROOT/GRZX/"
      }
    ]
  }
}
